CHANGES.rst
LICENSE
MANIFEST.in
README.rst
setup.py
changelog/__init__.py
changelog/command_line.py
changelog/tests/__init__.py
changelog/tests/test_command_line.py
changelog_suggest.egg-info/PKG-INFO
changelog_suggest.egg-info/SOURCES.txt
changelog_suggest.egg-info/dependency_links.txt
changelog_suggest.egg-info/entry_points.txt
changelog_suggest.egg-info/not-zip-safe
changelog_suggest.egg-info/top_level.txt