Metadata-Version: 1.1
Name: changelog-suggest
Version: 0.1.0
Summary: Create a suggested CHANGELOG from your git repos logs
Home-page: https://github.com/kirankoduru/changelog
Author: Kiran Koduru
Author-email: kiranrkoduru@gmail.com
License: MIT
Keywords: git log changelog python
Platform: UNKNOWN
Classifier: Environment :: Console
Classifier: Intended Audience :: Developers
Classifier: License :: OSI Approved :: MIT License
Classifier: Programming Language :: Python
Classifier: Programming Language :: Python :: 2.7
